Workbook
Name Slicer_Date: #N/A

Sheet Sheet1
A1: Sheet Name | B1: Purpose
A2: Dashboard | B2: Summary of sales, profits, top products, total revenue, and expenses
A3: Sales Entry | B3: Where users record daily sales per product (auto profit calc included)
A4: Product List | B4: Includes products, cost price, selling price, and auto profit per unit
A5: Expense Log | B5: For recording expenses like rent, electricity, transport, etc.
A6: Settings | B6: For drop-down values: product categories, payment types, etc.

Sheet pivot
A31: Product Name | B31: Sum of Selling Price (₦)
A32: Maltina can | B32: 4000
A33: Pen Pack | B33: 2800
A34: Bread | B34: 2300
A35: Body Lotion | B35: 1680
A36: Boxer | B36: 1600
A37: Grand Total | B37: 12380
A49: Category | B49: Sum of Selling Price (₦)
A50: Drinks | B50: 6000
A51: Stationery | B51: 2800
A52: Food | B52: 2300
A53: Beauty | B53: 1680
A54: Clothes | B54: 1600
A55: Electronics | B55: 1400
A56: Grand Total | B56: 15780

Sheet Sheet4
A1: Monthly sale | B1: Sum of Selling Price (₦)
A2: Jan | B2: 900
A3: Feb | B3: 1800
A4: Mar | B4: 940
A5: Apr | B5: 1440
A6: May | B6: 1240
A7: Jun | B7: 940
A8: Jul | B8: 400
A9: Aug | B9: 940
A10: Sep | B10: 440
A11: Oct | B11: 3300
A12: Nov | B12: 2000
A13: Dec | B13: 1440
A14: Grand Total | B14: 15780

Sheet Expense Log
A1: Date | B1: Expense Category | C1: Description | D1: Amount (₦) | E1: Payment Mode
A2: 46014 | B2: Utilities | C2: paid | D2: 23 | E2: Transfer
A3: 46015 | B3: Repairs | C3: pay gas | D3: 3500 | E3: POS
A4: 46016 | B4: Data | C4: monthly plan | D4: 1000 | E4: Transfer
A5: 46017 | B5: Marketing | C5: advertisement | D5: 1200 | E5: Others
A6: 46018 | B6: Utilities | C6: paid this month | D6: 1000 | E6: POS
A7: 46019 | B7: Data | C7: pay | D7: 4700 | E7: POS

Sheet Sales Entry
A1: Date | B1: Product Name | C1: Category | D1: Qty Sold | E1: Cost Price (₦) | F1: Selling Price (₦) | G1: Profit per Unit | H1: Total Profit (₦) | I1: Payment Mode
A2: 43924 | B2: Body Lotion | C2: =IFERROR(VLOOKUP(B2,'Product List'!B:G,2,),"") -> Beauty | D2: 5 | E2: =IFERROR(VLOOKUP(B2,'Product List'!B:G,3,FALSE),"") -> 120 | F2: =IFERROR(VLOOKUP(B2,'Product List'!B:G,4,FALSE),"") -> 240 | G2: =IFERROR(VLOOKUP(B2,'Product List'!B:G,5,FALSE),"") -> 120 | H2: =IF(D2="", "", D2 * G2) -> 600 | I2: Transfer
A3: 43954 | B3: Body Lotion | C3: =IFERROR(VLOOKUP(B3,'Product List'!B:G,2,),"") -> Beauty | D3: 6 | E3: =IFERROR(VLOOKUP(B3,'Product List'!B:G,3,FALSE),"") -> 120 | F3: =IFERROR(VLOOKUP(B3,'Product List'!B:G,4,FALSE),"") -> 240 | G3: =IFERROR(VLOOKUP(B3,'Product List'!B:G,5,FALSE),"") -> 120 | H3: =IF(D3="", "", D3 * G3) -> 720 | I3: POS
A4: 43985 | B4: Body Lotion | C4: =IFERROR(VLOOKUP(B4,'Product List'!B:G,2,),"") -> Beauty | D4: 5 | E4: =IFERROR(VLOOKUP(B4,'Product List'!B:G,3,FALSE),"") -> 120 | F4: =IFERROR(VLOOKUP(B4,'Product List'!B:G,4,FALSE),"") -> 240 | G4: =IFERROR(VLOOKUP(B4,'Product List'!B:G,5,FALSE),"") -> 120 | H4: =IF(D4="", "", D4 * G4) -> 600 | I4: Cash
A5: 44015 | B5: Earphone | C5: =IFERROR(VLOOKUP(B5,'Product List'!B:G,2,),"") -> Electronics | D5: 2 | E5: =IFERROR(VLOOKUP(B5,'Product List'!B:G,3,FALSE),"") -> 180 | F5: =IFERROR(VLOOKUP(B5,'Product List'!B:G,4,FALSE),"") -> 200 | G5: =IFERROR(VLOOKUP(B5,'Product List'!B:G,5,FALSE),"") -> 20 | H5: =IF(D5="", "", D5 * G5) -> 40 | I5: POS
A6: 44046 | B6: Body Lotion | C6: =IFERROR(VLOOKUP(B6,'Product List'!B:G,2,),"") -> Beauty | D6: 2 | E6: =IFERROR(VLOOKUP(B6,'Product List'!B:G,3,FALSE),"") -> 120 | F6: =IFERROR(VLOOKUP(B6,'Product List'!B:G,4,FALSE),"") -> 240 | G6: =IFERROR(VLOOKUP(B6,'Product List'!B:G,5,FALSE),"") -> 120 | H6: =IF(D6="", "", D6 * G6) -> 240 | I6: Transfer
A7: 44077 | B7: Body Lotion | C7: =IFERROR(VLOOKUP(B7,'Product List'!B:G,2,),"") -> Beauty | D7: 4 | E7: =IFERROR(VLOOKUP(B7,'Product List'!B:G,3,FALSE),"") -> 120 | F7: =IFERROR(VLOOKUP(B7,'Product List'!B:G,4,FALSE),"") -> 240 | G7: =IFERROR(VLOOKUP(B7,'Product List'!B:G,5,FALSE),"") -> 120 | H7: =IF(D7="", "", D7 * G7) -> 480 | I7: Others
A8: 44107 | B8: Coca cola | C8: =IFERROR(VLOOKUP(B8,'Product List'!B:G,2,),"") -> Drinks | D8: 9 | E8: =IFERROR(VLOOKUP(B8,'Product List'!B:G,3,FALSE),"") -> 900 | F8: =IFERROR(VLOOKUP(B8,'Product List'!B:G,4,FALSE),"") -> 1000 | G8: =IFERROR(VLOOKUP(B8,'Product List'!B:G,5,FALSE),"") -> 100 | H8: =IF(D8="", "", D8 * G8) -> 900 | I8: Transfer
A9: 44138 | B9: Maltina can | C9: =IFERROR(VLOOKUP(B9,'Product List'!B:G,2,),"") -> Drinks | D9: 10 | E9: =IFERROR(VLOOKUP(B9,'Product List'!B:G,3,FALSE),"") -> 700 | F9: =IFERROR(VLOOKUP(B9,'Product List'!B:G,4,FALSE),"") -> 1000 | G9: =IFERROR(VLOOKUP(B9,'Product List'!B:G,5,FALSE),"") -> 300 | H9: =IF(D9="", "", D9 * G9) -> 3000 | I9: POS
A10: 44168 | B10: Body Lotion | C10: =IFERROR(VLOOKUP(B10,'Product List'!B:G,2,),"") -> Beauty | D10: 2 | E10: =IFERROR(VLOOKUP(B10,'Product List'!B:G,3,FALSE),"") -> 120 | F10: =IFERROR(VLOOKUP(B10,'Product List'!B:G,4,FALSE),"") -> 240 | G10: =IFERROR(VLOOKUP(B10,'Product List'!B:G,5,FALSE),"") -> 120 | H10: =IF(D10="", "", D10 * G10) -> 240 | I10: Transfer
A11: 44168 | B11: Earphone | C11: =IFERROR(VLOOKUP(B11,'Product List'!B:G,2,),"") -> Electronics | D11: 3 | E11: =IFERROR(VLOOKUP(B11,'Product List'!B:G,3,FALSE),"") -> 180 | F11: =IFERROR(VLOOKUP(B11,'Product List'!B:G,4,FALSE),"") -> 200 | G11: =IFERROR(VLOOKUP(B11,'Product List'!B:G,5,FALSE),"") -> 20 | H11: =IF(D11="", "", D11 * G11) -> 60 | I11: Transfer
A12: 44199 | B12: Pen Pack | C12: =IFERROR(VLOOKUP(B12,'Product List'!B:G,2,),"") -> Stationery | D12: 5 | E12: =IFERROR(VLOOKUP(B12,'Product List'!B:G,3,FALSE),"") -> 500 | F12: =IFERROR(VLOOKUP(B12,'Product List'!B:G,4,FALSE),"") -> 700 | G12: =IFERROR(VLOOKUP(B12,'Product List'!B:G,5,FALSE),"") -> 200 | H12: =IF(D12="", "", D12 * G12) -> 1000 | I12: Transfer
A13: 44230 | B13: Boxer | C13: =IFERROR(VLOOKUP(B13,'Product List'!B:G,2,),"") -> Clothes | D13: 5 | E13: =IFERROR(VLOOKUP(B13,'Product List'!B:G,3,FALSE),"") -> 1300 | F13: =IFERROR(VLOOKUP(B13,'Product List'!B:G,4,FALSE),"") -> 1600 | G13: =IFERROR(VLOOKUP(B13,'Product List'!B:G,5,FALSE),"") -> 300 | H13: =IF(D13="", "", D13 * G13) -> 1500 | I13: Transfer
... A27: 44654 | B27: Earphone | C27: =IFERROR(VLOOKUP(B27,'Product List'!B:G,2,),"") -> Electronics | D27: 4 | E27: =IFERROR(VLOOKUP(B27,'Product List'!B:G,3,FALSE),"") -> 180 | F27: =IFERROR(VLOOKUP(B27,'Product List'!B:G,4,FALSE),"") -> 200 | G27: =IFERROR(VLOOKUP(B27,'Product List'!B:G,5,FALSE),"") -> 20 | H27: =IF(D27="", "", D27 * G27) -> 80 | I27: POS
A28: 44745 | B28: Coca cola | C28: =IFERROR(VLOOKUP(B28,'Product List'!B:G,2,),"") -> Drinks | D28: 4 | E28: =IFERROR(VLOOKUP(B28,'Product List'!B:G,3,FALSE),"") -> 900 | F28: =IFERROR(VLOOKUP(B28,'Product List'!B:G,4,FALSE),"") -> 1000 | G28: =IFERROR(VLOOKUP(B28,'Product List'!B:G,5,FALSE),"") -> 100 | H28: =IF(D28="", "", D28 * G28) -> 400
A29: 44749 | B29: Pepsi | C29: =IFERROR(VLOOKUP(B29,'Product List'!B:G,2,),"") -> Drinks | D29: 4 | E29: =IFERROR(VLOOKUP(B29,'Product List'!B:G,3,FALSE),"") -> 700 | F29: =IFERROR(VLOOKUP(B29,'Product List'!B:G,4,FALSE),"") -> 890 | G29: =IFERROR(VLOOKUP(B29,'Product List'!B:G,5,FALSE),"") -> 190 | H29: =IF(D29="", "", D29 * G29) -> 760

Sheet Product List
A1: Product ID | B1: Product Name | C1: Category | D1: Cost Price (₦) | E1: Selling Price (₦) | F1: Profit per Unit | G1: Stock Qty (Optional)
A2: P001 | B2: Bread | C2: Food | D2: 1000 | E2: 2300 | F2: =IF(AND(ISNUMBER(D2), ISNUMBER(E2)), E2 - D2, "") -> 1300 | G2: 20
A3: P002 | B3: Body Lotion | C3: Beauty | D3: 120 | E3: 240 | F3: =IF(AND(ISNUMBER(D3), ISNUMBER(E3)), E3 - D3, "") -> 120 | G3: 3
A4: P003 | B4: Earphone | C4: Electronics | D4: 180 | E4: 200 | F4: =IF(AND(ISNUMBER(D4), ISNUMBER(E4)), E4 - D4, "") -> 20 | G4: 3
A5: P004 | B5: Pen Pack | C5: Stationery | D5: 500 | E5: 700 | F5: =IF(AND(ISNUMBER(D5), ISNUMBER(E5)), E5 - D5, "") -> 200 | G5: 12
A6: P005 | B6: Coca cola | C6: Drinks | D6: 900 | E6: 1000 | F6: =IF(AND(ISNUMBER(D6), ISNUMBER(E6)), E6 - D6, "") -> 100 | G6: 12
A7: P006 | B7: Pepsi | C7: Drinks | D7: 700 | E7: 890 | F7: =IF(AND(ISNUMBER(D7), ISNUMBER(E7)), E7 - D7, "") -> 190 | G7: 12
A8: P007 | B8: Maltina can | C8: Drinks | D8: 700 | E8: 1000 | F8: =IF(AND(ISNUMBER(D8), ISNUMBER(E8)), E8 - D8, "") -> 300 | G8: 12
A9: P008 | B9: Bottle water 50Cl | C9: Drinks | D9: 700 | E9: 1000 | F9: =IF(AND(ISNUMBER(D9), ISNUMBER(E9)), E9 - D9, "") -> 300 | G9: 12
A10: P009 | B10: Fruit juice pack | C10: Drinks | D10: 700 | E10: 1000 | F10: =IF(AND(ISNUMBER(D10), ISNUMBER(E10)), E10 - D10, "") -> 300 | G10: 12
A11: P010 | B11: Indomie Super pack | C11: Food | D11: 1200 | E11: 2500 | F11: =IF(AND(ISNUMBER(D11), ISNUMBER(E11)), E11 - D11, "") -> 1300 | G11: 12
A12: P011 | B12: Spaghettti | C12: Food | D12: 1300 | E12: 2500 | F12: =IF(AND(ISNUMBER(D12), ISNUMBER(E12)), E12 - D12, "") -> 1200 | G12: 12
A13: P012 | B13: Vegetable Oil(1L) | C13: Food | D13: 1000 | E13: 2500 | F13: =IF(AND(ISNUMBER(D13), ISNUMBER(E13)), E13 - D13, "") -> 1500 | G13: 12
... A33: P032 | B33: Hair Cream | C33: Beauty | D33: 2300 | E33: 3500 | F33: =IF(AND(ISNUMBER(D33), ISNUMBER(E33)), E33 - D33, "") -> 1200 | G33: 12
F34: =IF(AND(ISNUMBER(D34), ISNUMBER(E34)), E34 - D34, "")
F35: =IF(AND(ISNUMBER(D35), ISNUMBER(E35)), E35 - D35, "")
F36: =IF(AND(ISNUMBER(D36), ISNUMBER(E36)), E36 - D36, "")
F37: =IF(AND(ISNUMBER(D37), ISNUMBER(E37)), E37 - D37, "")
F38: =IF(AND(ISNUMBER(D38), ISNUMBER(E38)), E38 - D38, "")
F39: =IF(AND(ISNUMBER(D39), ISNUMBER(E39)), E39 - D39, "")
F40: =IF(AND(ISNUMBER(D40), ISNUMBER(E40)), E40 - D40, "")
F41: =IF(AND(ISNUMBER(D41), ISNUMBER(E41)), E41 - D41, "")
F42: =IF(AND(ISNUMBER(D42), ISNUMBER(E42)), E42 - D42, "")
F43: =IF(AND(ISNUMBER(D43), ISNUMBER(E43)), E43 - D43, "")
F44: =IF(AND(ISNUMBER(D44), ISNUMBER(E44)), E44 - D44, "")
F45: =IF(AND(ISNUMBER(D45), ISNUMBER(E45)), E45 - D45, "")
... F70: =IF(AND(ISNUMBER(D70), ISNUMBER(E70)), E70 - D70, "")

Sheet Settings
A1: Drinks | B1: Payment Mode | D1: (Expense Category):
A2: Food | B2: Cash | D2: Rent
A3: Clothes | B3: Transfer | D3: Utilities
A4: Stationery | B4: POS | D4: Transport
A5: Electronics | B5: Others | D5: Data
A6: Beauty | D6: Repairs
A7: Furniture | D7: Inventory Purchase
D8: Marketing
D9: Miscellaneous

Sheet Dashboard

Sheet Metrics
A1: Label | B1: Description | C1: Formula (Sample)
A2: 🟢 Total Sales | B2: Total sales | C2: =SUMPRODUCT('Sales Entry'!D2:D29,'Sales Entry'!F2:F29) -> 147420
A3: 🔵 Total Cost | B3: Total cost of goods sold | C3: =SUMPRODUCT('Sales Entry'!E2:E29,'Sales Entry'!D2:D29) -> 101220
A4: 🟠 Total Profit | B4: Total profit from all sales | C4: =SUMPRODUCT('Sales Entry'!G2:G29,'Sales Entry'!D2:D29) -> 46200
A5: 🔴 Total Expenses | B5: Total expenses logged | C5: =SUM('Expense Log'!D2:D70) -> 11423
A6: 🟣 Net Profit | B6: Profit - Expenses | C6: =C4-C5 -> 34777
